[
    {
        "INDONESIA": [
            "id_ID"
        ]
    },
    {
        "MALAYSIA-SINGAPORE": [
            "MY",
            "SG"
        ]
    },
    {
        "THAILAND-VIETNAM-FILIPINA": [
            "TH",
            "VN",
            "id_PH"
        ]
    },
    {
        "CHINA & HK-JEPANG-KOREA SELATAN": [
            "CN",
            "HK",
            "id_JP",
            "id_KR",
            "TW",
            "id_MO"
        ]
    },
    {
        "AUSTRALIA-SELANDIA BARU": [
            "AU",
            "id_NZ"
        ]
    },
    {
        "EROPA": [
            "id_AT",
            "id_NL",
            "id_BE",
            "id_BG",
            "id_DK",
            "id_FI",
            "id_HU",
            "id_UK",
            "id_IE",
            "id_IT",
            "id_DE",
            "id_HR",
            "id_LU",
            "id_MT",
            "id_NO",
            "id_PL",
            "id_PT",
            "id_FR",
            "id_CZ",
            "id_RO",
            "id_RU",
            "id_RS",
            "id_ES",
            "id_SE",
            "id_CH",
            "id_TR",
            "id_UA",
            "id_GR"
        ]
    },
    {
        "DESTINASI-LAINNYA": [
            "id_SA",
            "id_AZ",
            "id_BH",
            "BD",
            "id_BY",
            "BN",
            "id_CL",
            "id_FJ",
            "id_GE",
            "IN",
            "id_IR",
            "id_IL",
            "id_KZ",
            "id_NC",
            "id_KH",
            "id_SB",
            "id_KW",
            "LA",
            "id_LB",
            "id_MK",
            "id_MV",
            "id_EG",
            "MM",
            "NP",
            "id_OM",
            "id_PK",
            "id_PW",
            "id_PG",
            "id_QA",
            "id_WS",
            "id_CY",
            "LK",
            "id_TP",
            "id_UAE",
            "id_VU",
            "id_JO",
            "id_US",
            "id_AR",
            "id_AW",
            "id_BR",
            "id_EC",
            "id_GU",
            "id_CA",
            "id_CO",
            "id_CU",
            "id_MX",
            "id_PA",
            "id_PE",
            "id_SR",
            "id_ZA",
            "id_AO",
            "id_ET",
            "id_GH",
            "id_CM",
            "id_KE",
            "id_CD",
            "id_LR",
            "id_MG",
            "id_MA",
            "id_NG",
            "id_RW",
            "id_SD",
            "id_TZ",
            "id_UG",
            "id_ZM"
        ]
    }
]